coho-0.4.dist-info/WHEEL
coho-0.4.dist-info/top_level.txt
coho-0.4.dist-info/METADATA
coho-0.4.dist-info/RECORD
coho/__init__.cpython-36m-x86_64-linux-gnu.so
coho/smiles.pyi
coho/smiles.cpython-36m-x86_64-linux-gnu.so
coho/smiles.c
coho/__init__.pyi
coho/__init__.c
coho/py.typed
